{"2023-08-13": {"price": {"open": 8.38, "max": 8.59, "min": 8.38, "close": 8.59, "prevClose": 8.44, "diff": 0.15000000000000036}, "numTrans": 7.0, "tradedShares": 7350.0, "amount": 62785.0}, "2023-08-14": {"price": {"open": 8.44, "max": 8.45, "min": 8.44, "close": 8.45, "prevClose": 8.59, "diff": -0.14000000000000057}, "numTrans": 5.0, "tradedShares": 3120.0, "amount": 26338.0}, "2023-08-15": {"price": {"open": 8.3, "max": 8.45, "min": 8.24, "close": "8.4500", "prevClose": 8.45, "diff": 0.0}, "numTrans": 7.0, "tradedShares": 5400.0, "amount": 44794.0}}